{
    "instruments": [
        {
            "figi": "BBG000DT5D52",
            "ticker": "ABEO",
            "classCode": "ABEO",
            "isin": "US00289Y2063",
            "lot": 1,
            "currency": "usd",
            "shortEnabledFlag": false,
            "name": "Abeona Therapeutics Inc.",
            "exchange": "nasdaq",
            "issueSize": "5878000",
            "countryOfRisk": "US",
            "countryOfRiskName": "\u0421\u043e\u0435\u0434\u0438\u043d\u0435\u043d\u043d\u044b\u0435 \u0428\u0442\u0430\u0442\u044b \u0410\u043c\u0435\u0440\u0438\u043a\u0438",
            "sector": "health_care",
            "issueSizePlan": "200000000",
            "nominal": {
                "currency": "usd",
                "units": "0",
                "nano": 10000000
            },
            "tradingStatus": "SECURITY_TRADING_STATUS_NOT_AVAILABLE_FOR_TRADING",
            "otcFlag": true,
            "buyAvailableFlag": false,
            "sellAvailableFlag": false,
            "divYieldFlag": false,
            "shareType": "SHARE_TYPE_COMMON",
            "apiTradeAvailableFlag": false,
            "uid": "d9e4a43b-bcbb-4ca3-8913-64ed186fa9a3",
            "realExchange": "REAL_EXCHANGE_OTC",
            "positionUid": "ba21f965-f837-477b-b6e8-57c8fdc24f75",
            "forIisFlag": false,
            "forQualInvestorFlag": true,
            "weekendFlag": false,
            "blockedTcaFlag": false,
            "liquidityFlag": true
        }
    ]
}