{
    "instruments": [
        {
            "figi": "BBG000DQLV23",
            "ticker": "BMY",
            "classCode": "SPBXM",
            "isin": "US1101221083",
            "lot": 1,
            "currency": "usd",
            "klong": {
                "units": "2",
                "nano": 0
            },
            "kshort": {
                "units": "2",
                "nano": 0
            },
            "dlong": {
                "units": "1",
                "nano": 0
            },
            "dshort": {
                "units": "1",
                "nano": 0
            },
            "dlongMin": {
                "units": "1",
                "nano": 0
            },
            "dshortMin": {
                "units": "1",
                "nano": 0
            },
            "shortEnabledFlag": false,
            "name": "Bristol-Myers Squibb",
            "exchange": "SPB_MORNING",
            "ipoDate": "1969-06-01T00:00:00Z",
            "issueSize": "2222113553",
            "countryOfRisk": "US",
            "countryOfRiskName": "\u0421\u043e\u0435\u0434\u0438\u043d\u0435\u043d\u043d\u044b\u0435 \u0428\u0442\u0430\u0442\u044b \u0410\u043c\u0435\u0440\u0438\u043a\u0438",
            "sector": "health_care",
            "issueSizePlan": "0",
            "nominal": {
                "currency": "usd",
                "units": "0",
                "nano": 100000000
            },
            "tradingStatus": "SECURITY_TRADING_STATUS_NORMAL_TRADING",
            "otcFlag": false,
            "buyAvailableFlag": true,
            "sellAvailableFlag": true,
            "divYieldFlag": true,
            "shareType": "SHARE_TYPE_COMMON",
            "minPriceIncrement": {
                "units": "0",
                "nano": 10000000
            },
            "apiTradeAvailableFlag": true,
            "uid": "02416f52-5a61-4701-88f6-03f978da7ae4",
            "realExchange": "REAL_EXCHANGE_RTS",
            "positionUid": "482e3c5c-8aa8-4db2-8fff-3d57f027cf79",
            "forIisFlag": true,
            "forQualInvestorFlag": true,
            "weekendFlag": false,
            "blockedTcaFlag": false,
            "liquidityFlag": false,
            "first1minCandleDate": "2018-01-23T13:20:00Z",
            "first1dayCandleDate": "1988-09-12T00:00:00Z"
        },
        {
            "figi": "US1101221083",
            "ticker": "US1101221083",
            "classCode": "SPBXM_OTC",
            "isin": "US1101221083",
            "lot": 1,
            "currency": "usd",
            "shortEnabledFlag": false,
            "name": "Bristol-Myers Squibb",
            "exchange": "dealer_int_exchange",
            "ipoDate": "1969-06-01T00:00:00Z",
            "issueSize": "2222113553",
            "countryOfRisk": "US",
            "countryOfRiskName": "\u0421\u043e\u0435\u0434\u0438\u043d\u0435\u043d\u043d\u044b\u0435 \u0428\u0442\u0430\u0442\u044b \u0410\u043c\u0435\u0440\u0438\u043a\u0438",
            "sector": "health_care",
            "issueSizePlan": "0",
            "nominal": {
                "currency": "usd",
                "units": "0",
                "nano": 100000000
            },
            "tradingStatus": "SECURITY_TRADING_STATUS_NOT_AVAILABLE_FOR_TRADING",
            "otcFlag": false,
            "buyAvailableFlag": true,
            "sellAvailableFlag": true,
            "divYieldFlag": true,
            "shareType": "SHARE_TYPE_COMMON",
            "minPriceIncrement": {
                "units": "0",
                "nano": 10000000
            },
            "apiTradeAvailableFlag": false,
            "uid": "58c53a56-aedb-4f27-b5a3-388e01c6d32b",
            "realExchange": "REAL_EXCHANGE_OTC",
            "positionUid": "35f8caf2-7ca3-4c7a-b542-42ae055f6bc1",
            "forIisFlag": false,
            "forQualInvestorFlag": true,
            "weekendFlag": false,
            "blockedTcaFlag": true,
            "liquidityFlag": false
        }
    ]
}