{
    "instruments": [
        {
            "figi": "BBG005RVNVY9",
            "ticker": "CBPX",
            "classCode": "SPBXM",
            "isin": "US2111711030",
            "lot": 1,
            "currency": "usd",
            "shortEnabledFlag": false,
            "name": "Continental Building Products",
            "exchange": "SPB",
            "ipoDate": "2004-04-14T00:00:00Z",
            "issueSize": "38420573",
            "countryOfRisk": "US",
            "countryOfRiskName": "\u0421\u043e\u0435\u0434\u0438\u043d\u0435\u043d\u043d\u044b\u0435 \u0428\u0442\u0430\u0442\u044b \u0410\u043c\u0435\u0440\u0438\u043a\u0438",
            "sector": "industrials",
            "issueSizePlan": "190000000",
            "nominal": {
                "currency": "usd",
                "units": "0",
                "nano": 1000000
            },
            "tradingStatus": "SECURITY_TRADING_STATUS_NOT_AVAILABLE_FOR_TRADING",
            "otcFlag": false,
            "buyAvailableFlag": true,
            "sellAvailableFlag": true,
            "divYieldFlag": false,
            "shareType": "SHARE_TYPE_COMMON",
            "minPriceIncrement": {
                "units": "0",
                "nano": 10000000
            },
            "apiTradeAvailableFlag": false,
            "uid": "8f548694-413c-4312-b0be-8a9165797970",
            "realExchange": "REAL_EXCHANGE_RTS",
            "positionUid": "ff9d5b32-f2b9-4dd3-a73a-620dc6521170",
            "forIisFlag": true,
            "forQualInvestorFlag": false,
            "weekendFlag": false,
            "blockedTcaFlag": false,
            "liquidityFlag": false,
            "first1minCandleDate": "2019-10-31T13:43:00Z",
            "first1dayCandleDate": "2019-10-31T07:00:00Z"
        }
    ]
}