{
    "instruments": [
        {
            "figi": "US5246601075",
            "ticker": "US5246601075",
            "classCode": "SPBXM_OTC",
            "isin": "US5246601075",
            "lot": 1,
            "currency": "usd",
            "shortEnabledFlag": false,
            "name": "Leggett & Platt",
            "exchange": "Issuance",
            "ipoDate": "1967-03-29T00:00:00Z",
            "issueSize": "133298914",
            "countryOfRisk": "US",
            "countryOfRiskName": "\u0421\u043e\u0435\u0434\u0438\u043d\u0435\u043d\u043d\u044b\u0435 \u0428\u0442\u0430\u0442\u044b \u0410\u043c\u0435\u0440\u0438\u043a\u0438",
            "sector": "consumer",
            "issueSizePlan": "0",
            "nominal": {
                "currency": "usd",
                "units": "0",
                "nano": 10000000
            },
            "tradingStatus": "SECURITY_TRADING_STATUS_NOT_AVAILABLE_FOR_TRADING",
            "otcFlag": false,
            "buyAvailableFlag": false,
            "sellAvailableFlag": false,
            "divYieldFlag": true,
            "shareType": "SHARE_TYPE_COMMON",
            "minPriceIncrement": {
                "units": "0",
                "nano": 10000000
            },
            "apiTradeAvailableFlag": false,
            "uid": "61910f04-c1cb-4a1b-9ad6-f64e774273d0",
            "realExchange": "REAL_EXCHANGE_OTC",
            "positionUid": "96d60c31-ed46-40e5-99bc-8d695bfca1a5",
            "forIisFlag": false,
            "forQualInvestorFlag": true,
            "weekendFlag": false,
            "blockedTcaFlag": true,
            "liquidityFlag": false
        },
        {
            "figi": "BBG000BN53G7",
            "ticker": "LEG",
            "classCode": "SPBXM",
            "isin": "US5246601075",
            "lot": 1,
            "currency": "usd",
            "shortEnabledFlag": false,
            "name": "Leggett & Platt",
            "exchange": "SPB_MORNING",
            "ipoDate": "1967-03-29T00:00:00Z",
            "issueSize": "133298914",
            "countryOfRisk": "US",
            "countryOfRiskName": "\u0421\u043e\u0435\u0434\u0438\u043d\u0435\u043d\u043d\u044b\u0435 \u0428\u0442\u0430\u0442\u044b \u0410\u043c\u0435\u0440\u0438\u043a\u0438",
            "sector": "consumer",
            "issueSizePlan": "0",
            "nominal": {
                "currency": "usd",
                "units": "0",
                "nano": 10000000
            },
            "tradingStatus": "SECURITY_TRADING_STATUS_NORMAL_TRADING",
            "otcFlag": false,
            "buyAvailableFlag": true,
            "sellAvailableFlag": true,
            "divYieldFlag": true,
            "shareType": "SHARE_TYPE_COMMON",
            "minPriceIncrement": {
                "units": "0",
                "nano": 10000000
            },
            "apiTradeAvailableFlag": true,
            "uid": "cf57d7fe-a7ea-4969-a23f-2f22e296b3b6",
            "realExchange": "REAL_EXCHANGE_RTS",
            "positionUid": "effac8b0-fc7b-4089-8253-78a5a3a427d5",
            "forIisFlag": true,
            "forQualInvestorFlag": true,
            "weekendFlag": false,
            "blockedTcaFlag": false,
            "liquidityFlag": false,
            "first1minCandleDate": "2018-01-23T14:32:00Z",
            "first1dayCandleDate": "1988-09-12T00:00:00Z"
        }
    ]
}