{
    "instruments": [
        {
            "figi": "BBG000BLCR07",
            "ticker": "7974",
            "classCode": "7974",
            "isin": "JP3756600007",
            "lot": 1,
            "currency": "jpy",
            "shortEnabledFlag": false,
            "name": "Nintendo",
            "exchange": "Issuance",
            "issueSize": "1298690000",
            "countryOfRisk": "JP",
            "countryOfRiskName": "",
            "sector": "telecom",
            "issueSizePlan": "4000000000",
            "nominal": {
                "currency": "jpy",
                "units": "0",
                "nano": 0
            },
            "tradingStatus": "SECURITY_TRADING_STATUS_NOT_AVAILABLE_FOR_TRADING",
            "otcFlag": true,
            "buyAvailableFlag": false,
            "sellAvailableFlag": false,
            "divYieldFlag": false,
            "shareType": "SHARE_TYPE_COMMON",
            "apiTradeAvailableFlag": false,
            "uid": "3466ebbc-1823-467e-8521-6f0522b6f784",
            "realExchange": "REAL_EXCHANGE_OTC",
            "positionUid": "68b51a6c-6b16-4bc7-9ae6-dc7dd3ef18be",
            "forIisFlag": false,
            "forQualInvestorFlag": true,
            "weekendFlag": false,
            "blockedTcaFlag": false,
            "liquidityFlag": true
        }
    ]
}