{
    "instruments": [
        {
            "figi": "BBG00Z5H4460",
            "ticker": "XPDI",
            "classCode": "XPDI",
            "isin": "US7391901060",
            "lot": 1,
            "currency": "usd",
            "shortEnabledFlag": false,
            "name": "SPAC Power & Digital Infrastructure",
            "exchange": "Issuance",
            "issueSize": "0",
            "countryOfRisk": "US",
            "countryOfRiskName": "\u0421\u043e\u0435\u0434\u0438\u043d\u0435\u043d\u043d\u044b\u0435 \u0428\u0442\u0430\u0442\u044b \u0410\u043c\u0435\u0440\u0438\u043a\u0438",
            "sector": "financial",
            "issueSizePlan": "0",
            "nominal": {
                "currency": "usd",
                "units": "0",
                "nano": 100000
            },
            "tradingStatus": "SECURITY_TRADING_STATUS_NOT_AVAILABLE_FOR_TRADING",
            "otcFlag": true,
            "buyAvailableFlag": false,
            "sellAvailableFlag": false,
            "divYieldFlag": false,
            "shareType": "SHARE_TYPE_COMMON",
            "apiTradeAvailableFlag": false,
            "uid": "214c71f6-aa6e-4ff9-a2a6-dccc53f810d2",
            "realExchange": "REAL_EXCHANGE_OTC",
            "positionUid": "930f11be-9bcf-4cef-8635-18b65e5c87d4",
            "forIisFlag": false,
            "forQualInvestorFlag": true,
            "weekendFlag": false,
            "blockedTcaFlag": false,
            "liquidityFlag": true
        }
    ]
}